ec2instance/__init__.py
ec2instance/main.py
ec2instance-1.9.dist-info/METADATA
ec2instance-1.9.dist-info/WHEEL
ec2instance-1.9.dist-info/entry_points.txt
ec2instance-1.9.dist-info/RECORD
