Metadata-Version: 2.4
Name: ec2instance
Version: 1.9
Summary: Launch new EC2 instances easily and quickly with one command
Project-URL: Homepage, https://github.com/personalcomputer/ec2instance
Author-email: John Miller <john@johngm.com>
Classifier: License :: OSI Approved :: MIT License
Classifier: Programming Language :: Python
Classifier: Programming Language :: Python :: 3
Classifier: Programming Language :: Python :: Implementation :: CPython
Requires-Python: >=3.7.0
Requires-Dist: boto3
Requires-Dist: cryptography
Requires-Dist: iso8601
